CHANGES.md
MANIFEST.in
README.md
setup.py
django_mapbox_baselayer.egg-info/PKG-INFO
django_mapbox_baselayer.egg-info/SOURCES.txt
django_mapbox_baselayer.egg-info/dependency_links.txt
django_mapbox_baselayer.egg-info/requires.txt
django_mapbox_baselayer.egg-info/top_level.txt
mapbox_baselayer/VERSION.md
mapbox_baselayer/__init__.py
mapbox_baselayer/admin.py
mapbox_baselayer/apps.py
mapbox_baselayer/models.py
mapbox_baselayer/urls.py
mapbox_baselayer/views.py
mapbox_baselayer/locale/en/LC_MESSAGES/django.po
mapbox_baselayer/locale/fr/LC_MESSAGES/django.po
mapbox_baselayer/management/__init__.py
mapbox_baselayer/management/commands/__init__.py
mapbox_baselayer/management/commands/install_ign_baselayer.py
mapbox_baselayer/management/commands/install_mapbox_baselayer.py
mapbox_baselayer/management/commands/install_opentopomap_baselayer.py
mapbox_baselayer/management/commands/install_osm_baselayer.py
mapbox_baselayer/migrations/0001_initial.py
mapbox_baselayer/migrations/0002_auto_20191129_0942.py
mapbox_baselayer/migrations/0003_auto_20191202_0937.py
mapbox_baselayer/migrations/0004_auto_20191202_1834.py
mapbox_baselayer/migrations/0005_auto_20191202_1840.py
mapbox_baselayer/migrations/0006_alter_baselayertile_id_alter_mapbaselayer_id_and_more.py
mapbox_baselayer/migrations/0007_alter_mapbaselayer_attribution.py
mapbox_baselayer/migrations/__init__.py
mapbox_baselayer/tests/__init__.py
mapbox_baselayer/tests/test_commands.py
mapbox_baselayer/tests/test_models.py
mapbox_baselayer/tests/test_views.py